Metadata-Version: 2.1
Name: google_trans_new
Version: 1.1.9
Summary: A free and unlimited python tools for google translate api.
Home-page: https://github.com/lushan88a/google_trans_new
Author: LuShan
Author-email: 188301710@qq.com
Maintainer: LuShan
Maintainer-email: 188301710@qq.com
License: MIT
Platform: all
Classifier: License :: OSI Approved :: MIT License
Classifier: Programming Language :: Python
Classifier: Programming Language :: Python :: 3
Classifier: Programming Language :: Python :: 3.6
Classifier: Programming Language :: Python :: Implementation :: CPython
Classifier: Programming Language :: Python :: Implementation :: PyPy
